kenkui/__init__.py
kenkui/__main__.py
kenkui/helpers.py
kenkui/parsing.py
kenkui/workers.py
kenkui/samples/__init__.py
kenkui/voices/__init__.py
kenkui-0.3.3.dist-info/licenses/LICENSE
kenkui-0.3.3.dist-info/METADATA
kenkui-0.3.3.dist-info/WHEEL
kenkui-0.3.3.dist-info/entry_points.txt
kenkui-0.3.3.dist-info/top_level.txt
kenkui-0.3.3.dist-info/RECORD
