Metadata-Version: 2.4
Name: kenkui
Version: 0.3.3
Summary: Convert Ebooks to Audiobooks with [custom] voice samples
Author-email: Sumner MacArthur <spn1kolat3sla@gmail.com>
License:                     GNU GENERAL PUBLIC LICENSE
Project-URL: Homepage, https://github.com/D1zzl3D0p/kenkui
Project-URL: Bug Tracker, https://github.com/D1zzl3D0p/kenkui/issues
Classifier: Programming Language :: Python :: 3
Classifier: Operating System :: OS Independent
Classifier: License :: OSI Approved :: GNU General Public License v3 (GPLv3)
Requires-Python: >=3.7
License-File: LICENSE
Requires-Dist: beautifulsoup4>=4.14.0
Requires-Dist: EbookLib>=0.20
Requires-Dist: rich>=14.2.0
Requires-Dist: scipy>=1.17.0
Requires-Dist: huggingface_hub>=1.3.0
Requires-Dist: pydub>=0.25.0
Requires-Dist: pocket-tts>=1.0.0
Dynamic: license-file
